[
  {
    "id": "earring-01",
    "title": "Gold Stud Earring",
    "category": "earring",
    "type": "stud",
    "description": "Lightweight gold stud earring suitable for ear pasting and daily wear. Comfortable, skin-safe, and ideal for all age groups.",
    "material": "Gold",
    "purity": "22K",
    "use_case": ["ear-pasting", "daily-wear"],
    "images": [
      "https://images.unsplash.com/photo-1600180758890-6b94519a8ba6?q=80&w=800",
      "https://images.unsplash.com/photo-1585386959984-a41552231693?q=80&w=800"
    ],
    "price": 2500,
    "price_note": "Prices may vary based on gold rate and design",
    "cta": {
      "primary": "call",
      "secondary": "whatsapp"
    },
    "featured": true,
    "visible": true,
    "order": 1
  },
  {
    "id": "earring-02",
    "title": "Traditional Gold Hoop",
    "category": "earring",
    "type": "hoop",
    "description": "Classic traditional gold hoop earring with a smooth finish. Suitable for regular use and special occasions.",
    "material": "Gold",
    "purity": "22K",
    "use_case": ["daily-wear", "traditional"],
    "images": [
      "https://images.unsplash.com/photo-1620625515032-6ed0c1790c75?q=80&w=800"
    ],
    "price": 4200,
    "price_note": "Prices may vary based on gold rate and design",
    "cta": {
      "primary": "call"
    },
    "featured": false,
    "visible": true,
    "order": 2
  },
  {
    "id": "earring-03",
    "title": "Kids Gold Ear Pasting Stud",
    "category": "earring",
    "type": "stud",
    "description": "Small, lightweight gold stud designed especially for kids ear pasting. Smooth edges and hygienic design.",
    "material": "Gold",
    "purity": "22K",
    "use_case": ["ear-pasting", "kids"],
    "images": [
      "https://images.unsplash.com/photo-1599643477877-530eb83abc8e?q=80&w=800"
    ],
    "price": 1800,
    "price_note": "Prices may vary based on gold rate and design",
    "cta": {
      "primary": "call",
      "secondary": "whatsapp"
    },
    "featured": true,
    "visible": true,
    "order": 3
  }
]
